{"currentpage":636,"totalpages":815,"qualifiedathletes":0,"athletes":[{"userid":"1032790","name":"Pierre Labour","regionid":"7","affiliateid":"17591","divisionid":"1","highlight":0,"age":34,"region":"Europe","height":"180 cm","weight":"95 kg","profilepic":"https:\/\/profilepicsbucket.crossfit.com\/939f4-P1032790_1-184.jpg","overallrank":"31751","overallscore":"143351","affiliate":"","division":1,"scores":[{"workoutrank":"30771","workoutresult":"--","scoreidentifier":"ca2c0abbcbbfa4b05750","scoredisplay":"13:58 - s","scoredetails":{"time":838,"breakdown":"225 reps","judge":"Alexandre Dool","affiliate":"Rupella CrossFit"},"video":0},{"workoutrank":"31262","workoutresult":"--","scoreidentifier":"f53e874c9c89fd7f5c09","scoredisplay":"132 reps - s","scoredetails":{"time":475,"breakdown":"3 Rounds\n50-ft lunges\n16 Pull-ups\n4 Power cleans\n","judge":"Thomas Picard","affiliate":"Rupella CrossFit"},"video":0},{"workoutrank":"32418","workoutresult":"--","scoreidentifier":"--","scoredisplay":"0","scoredetails":null,"video":"--"},{"workoutrank":"26088","workoutresult":"--","scoreidentifier":"c531857a65efc8169990","scoredisplay":"268 reps - s","scoredetails":{"time":657,"breakdown":"1 Round\n48 Deadlifts","judge":"Thomas Picard","affiliate":"Rupella CrossFit"},"video":0},{"workoutrank":"22812","workoutresult":"--","scoreidentifier":"d201fc219a2778fc150f","scoredisplay":"8:29 - s","scoredetails":{"time":509,"breakdown":"440 reps","judge":"Thomas Picard","affiliate":"Rupella CrossFit"},"video":0}]},{"userid":"1011314","name":"Simon Beck","regionid":"7","affiliateid":"15782","divisionid":"1","highlight":0,"age":30,"region":"Europe","height":"176 cm","weight":"73 kg","profilepic":"https:\/\/profilepicsbucket.crossfit.com\/pukie.png","overallrank":"31752","overallscore":"143353","affiliate":"","division":1,"scores":[{"workoutrank":"32407","workoutresult":"--","scoreidentifier":"cc15b985083bf938f494","scoredisplay":"16:48 - s","scoredetails":{"time":1008,"breakdown":"225 reps\nJudged by Sarah Ruesch\nat CrossFit Langnau"},"video":"0"},{"workoutrank":"29468","workoutresult":"--","scoreidentifier":"fa04c7068b1a5aca0142","scoredisplay":"166 reps - s","scoredetails":{"time":600,"breakdown":"4 Rounds\n50-ft lunges\n16 Knee-raises\n4 Power cleans\n","judge":"Sarah Ruesch","affiliate":"CrossFit Langnau"},"video":0},{"workoutrank":"31259","workoutresult":"--","scoreidentifier":"498556b14b38a1481f17","scoredisplay":"55 reps - s","scoredetails":{"time":226,"breakdown":"4 Rounds\n7 Pull-ups","judge":"Sarah Ruesch","affiliate":"CrossFit Langnau"},"video":0},{"workoutrank":"27105","workoutresult":"--","scoreidentifier":"79877421046fa4c6c832","scoredisplay":"227 reps - s","scoredetails":{"time":762,"breakdown":"1 Round\n7 Deadlifts","judge":"Sarah Ruesch","affiliate":"CrossFit Langnau"},"video":0},{"workoutrank":"23114","workoutresult":"--","scoreidentifier":"fa06d86361abe6324957","scoredisplay":"8:58 - s","scoredetails":{"time":538,"breakdown":"440 reps","judge":"Sarah Ruesch","affiliate":"CrossFit Langnau"},"video":0}]},{"userid":"925528","name":"Jose Francisco Molina L\u00f3pez","regionid":"7","affiliateid":"12686","divisionid":"1","highlight":0,"age":30,"region":"Europe","height":"178 cm","weight":"79 kg","profilepic":"https:\/\/profilepicsbucket.crossfit.com\/596ad-P925528_1-184.jpg","overallrank":"31753","overallscore":"143354","affiliate":"","division":1,"scores":[{"workoutrank":"33784","workoutresult":"--","scoreidentifier":"39c93bfc674a76938f38","scoredisplay":"18:27 - s","scoredetails":{"time":1107,"breakdown":"225 reps\nJudged by Matiu Brown\nat CrossFit LCS"},"video":"0"},{"workoutrank":"28635","workoutresult":"--","scoreidentifier":"d372aa291523140cb797","scoredisplay":"180 reps - s","scoredetails":{"time":653,"breakdown":"5 Rounds\n50-ft lunges\n","judge":"Anuska Peguero","affiliate":"CrossFit LCS"},"video":0},{"workoutrank":"28224","workoutresult":"--","scoreidentifier":"e065873e13fb76473e8f","scoredisplay":"94 reps - s","scoredetails":{"time":426,"breakdown":"7 Rounds\n8 Pull-ups\n2 Snatches","judge":"Anuska Peguero","affiliate":"CrossFit LCS"},"video":0},{"workoutrank":"26807","workoutresult":"--","scoreidentifier":"701f3462af40f39d3576","scoredisplay":"236 reps - s","scoredetails":{"time":730,"breakdown":"1 Round\n16 Deadlifts","judge":"Anuska Peguero","affiliate":"CrossFit LCS"},"video":0},{"workoutrank":"25904","workoutresult":"--","scoreidentifier":"f6625469b46750291968","scoredisplay":"12:09 - s","scoredetails":{"time":729,"breakdown":"440 reps","judge":"Anuska Peguero","affiliate":"CrossFit LCS"},"video":0}]},{"userid":"883522","name":"Stephen Lozier","regionid":"7","affiliateid":"0","divisionid":"1","highlight":0,"age":23,"region":"Europe","height":"173 cm","weight":"65 kg","profilepic":"https:\/\/profilepicsbucket.crossfit.com\/33a7c-P883522_1-184.jpg","overallrank":"31754","overallscore":"143360","affiliate":"","division":1,"scores":[{"workoutrank":"30951","workoutresult":"--","scoreidentifier":"af96ddbeb05c174d492b","scoredisplay":"14:27 - s","scoredetails":{"time":867,"breakdown":"225 reps\nJudged by Anne Guion\nat CrossFit Brest"},"video":"0"},{"workoutrank":"28294","workoutresult":"--","scoreidentifier":"e6521ee27458368bf58d","scoredisplay":"199 reps - s","scoredetails":{"time":623,"breakdown":"5 Rounds\n50-ft lunges\n16 Knee-raises\n3 Power cleans\n","judge":"Anne Guion","affiliate":"CrossFit Brest"},"video":0},{"workoutrank":"26599","workoutresult":"--","scoreidentifier":"dbcbf065364f2dc11ac7","scoredisplay":"119 reps - s","scoredetails":{"time":660,"breakdown":"9 Rounds\n9 Pull-ups\n2 Snatches","judge":"Bihannic Kevin","affiliate":"CrossFit Brest"},"video":0},{"workoutrank":"28393","workoutresult":"--","scoreidentifier":"aef2979cb4da5170cb0b","scoredisplay":"205 reps - s","scoredetails":{"time":590,"breakdown":"55 Deadlifts\n55 Wall-balls\n55 Calories\n40 Push-ups","judge":"Jonathan Klotz","affiliate":"CrossFit Black Owl"},"video":0},{"workoutrank":"29123","workoutresult":"--","scoreidentifier":"--","scoredisplay":"0","scoredetails":null,"video":"--"}]},{"userid":"894071","name":"Tom\u00e1\u0161 Bedn\u00e1\u0159","regionid":"7","affiliateid":"0","divisionid":"3","highlight":0,"age":47,"region":"Europe","height":"178 cm","weight":"85 kg","profilepic":"https:\/\/profilepicsbucket.crossfit.com\/pukie.png","overallrank":"31755","overallscore":"143368","affiliate":"","division":1,"scores":[{"workoutrank":"33802","workoutresult":"--","scoreidentifier":"45f0a8ec0192d4c0ea00","scoredisplay":"18:28 - s","scoredetails":{"time":1108,"breakdown":"225 reps"},"video":"1"},{"workoutrank":"30348","workoutresult":"--","scoreidentifier":"9c58251b81517b44da7f","scoredisplay":"145 reps - s","scoredetails":{"time":677,"breakdown":"4 Rounds\n45-ft lunges\n"},"video":"1"},{"workoutrank":"29208","workoutresult":"--","scoreidentifier":"3ec7d9d5abdc4486c5c7","scoredisplay":"80 reps - s","scoredetails":{"time":479,"breakdown":"6 Rounds\n8 Pull-ups"},"video":"1"},{"workoutrank":"26753","workoutresult":"--","scoreidentifier":"60d79f967db30e3aa005","scoredisplay":"238 reps - s","scoredetails":{"time":740,"breakdown":"1 Round\n18 Deadlifts"},"video":"1"},{"workoutrank":"23257","workoutresult":"--","scoreidentifier":"8198a5abfeaa9b8e1f7f","scoredisplay":"9:09 - s","scoredetails":{"time":549,"breakdown":"440 reps"},"video":"1"}]},{"userid":"969100","name":"Dmitriy Morgunov","regionid":"7","affiliateid":"7240","divisionid":"1","highlight":0,"age":30,"region":"Europe","height":"186 cm","weight":"88 kg","profilepic":"https:\/\/profilepicsbucket.crossfit.com\/pukie.png","overallrank":"31756","overallscore":"143378","affiliate":"","division":1,"scores":[{"workoutrank":"37098","workoutresult":"--","scoreidentifier":"--","scoredisplay":"0","scoredetails":null,"video":"--"},{"workoutrank":"30145","workoutresult":"--","scoreidentifier":"66c8db50dafe4d0cf5d3","scoredisplay":"146 reps - s","scoredetails":{"time":630,"breakdown":"4 Rounds\n50-ft lunges\n","judge":"yann guermeur","affiliate":"CrossFit W950"},"video":0},{"workoutrank":"26861","workoutresult":"--","scoreidentifier":"e3abd47af796ce86a39b","scoredisplay":"117 reps - s","scoredetails":{"time":718,"breakdown":"9 Rounds\n9 Pull-ups","judge":"yann guermeur","affiliate":"CrossFit W950"},"video":0},{"workoutrank":"29281","workoutresult":"--","scoreidentifier":"482734508096d44399ac","scoredisplay":"195 reps - s","scoredetails":{"time":659,"breakdown":"55 Deadlifts\n55 Wall-balls\n55 Calories\n30 Push-ups","judge":"yann guermeur","affiliate":"CrossFit W950"},"video":0},{"workoutrank":"19993","workoutresult":"--","scoreidentifier":"6cc1791eec91c096a2f3","scoredisplay":"38:00","scoredetails":{"time":2280,"breakdown":"440 reps","judge":"yann guermeur","affiliate":"CrossFit W950"},"video":0}]},{"userid":"986828","name":"Neil Munro","regionid":"7","affiliateid":"1499","divisionid":"1","highlight":0,"age":30,"region":"Europe","height":"6'4\"","weight":"97 kg","profilepic":"https:\/\/profilepicsbucket.crossfit.com\/pukie.png","overallrank":"31757","overallscore":"143380","affiliate":"","division":1,"scores":[{"workoutrank":"32043","workoutresult":"--","scoreidentifier":"a669049c3a6b812a23c7","scoredisplay":"16:21 - s","scoredetails":{"time":981,"breakdown":"225 reps\nJudged by Sam McCluskey\nat FFD CrossFit"},"video":"0"},{"workoutrank":"34748","workoutresult":"--","scoreidentifier":"--","scoredisplay":"0","scoredetails":null,"video":"--"},{"workoutrank":"27086","workoutresult":"--","scoreidentifier":"9fe9ce68fe96b8bf391b","scoredisplay":"106 reps - s","scoredetails":{"time":366,"breakdown":"8 Rounds\n8 Pull-ups\n2 Snatches","judge":"Loz ogilvie","affiliate":"CrossFit Aberdeen"},"video":0},{"workoutrank":"24709","workoutresult":"--","scoreidentifier":"a77acd181fb77b63c4b4","scoredisplay":"95 reps","scoredetails":{"time":600,"breakdown":"55 Deadlifts\n40 Wall-balls","judge":"Richard Foster","affiliate":"CrossFit Aberdeen"},"video":0},{"workoutrank":"24794","workoutresult":"--","scoreidentifier":"9caafc7b26954a03601e","scoredisplay":"10:48 - s","scoredetails":{"time":648,"breakdown":"440 reps","judge":"Andrzej Lange","affiliate":"CrossFit Aberdeen"},"video":0}]},{"userid":"1001805","name":"Sami Varelius","regionid":"7","affiliateid":"4415","divisionid":"1","highlight":0,"age":23,"region":"Europe","height":"","weight":"","profilepic":"https:\/\/profilepicsbucket.crossfit.com\/pukie.png","overallrank":"31758","overallscore":"143383","affiliate":"","division":1,"scores":[{"workoutrank":"23469","workoutresult":"--","scoreidentifier":"a06fbf595d30f7ddf0a8","scoredisplay":"192 reps","scoredetails":{"time":1016,"breakdown":"10 DB Snatches\n15 Burpees\n20 DB Snatches\n15 Burpees\n30 DB Snatches\n15 Burpees\n40 DB Snatches\n15 Burpees\n32 DB Snatches\n\nJudged by Pia Kokko\nat CrossFit Central NLA"},"video":"0"},{"workoutrank":"26605","workoutresult":"--","scoreidentifier":"c1717b175c9860aa0ae8","scoredisplay":"68 reps","scoredetails":{"time":359,"breakdown":"2 Rounds\n0-ft lunges\n","judge":"Jukka Tolvanen","affiliate":"CrossFit Central NLA"},"video":0},{"workoutrank":"32418","workoutresult":"--","scoreidentifier":"--","scoredisplay":"0","scoredetails":null,"video":"--"},{"workoutrank":"31768","workoutresult":"--","scoreidentifier":"--","scoredisplay":"0","scoredetails":null,"video":"--"},{"workoutrank":"29123","workoutresult":"--","scoreidentifier":"--","scoredisplay":"0","scoredetails":null,"video":"--"}]},{"userid":"937540","name":"Jamie Bennett","regionid":"7","affiliateid":"13222","divisionid":"16","highlight":0,"age":17,"region":"Europe","height":"183 cm","weight":"94 kg","profilepic":"https:\/\/profilepicsbucket.crossfit.com\/pukie.png","overallrank":"31758","overallscore":"143383","affiliate":"","division":1,"scores":[{"workoutrank":"29304","workoutresult":"--","scoreidentifier":"17c377b9c318a2c9dd86","scoredisplay":"149 reps","scoredetails":{"time":960,"breakdown":"10 DB Snatches\n15 Burpees\n20 DB Snatches\n15 Burpees\n30 DB Snatches\n15 Burpees\n40 DB Snatches\n4 Burpees\n\nJudged by Andrew Ridge\nat CrossFit Fierce Spirit"},"video":"0"},{"workoutrank":"27210","workoutresult":"--","scoreidentifier":"40277984af0c5bd288a7","scoredisplay":"49 reps","scoredetails":{"time":486,"breakdown":"1 Rounds\n50-ft lunges\n5 T2B\n","judge":"Andrew Ridge","affiliate":"CrossFit Fierce Spirit"},"video":0},{"workoutrank":"32418","workoutresult":"--","scoreidentifier":"--","scoredisplay":"0","scoredetails":null,"video":"--"},{"workoutrank":"25328","workoutresult":"--","scoreidentifier":"37b3e18c3739545e72f8","scoredisplay":"70 reps","scoredetails":{"time":471,"breakdown":"55 Deadlifts\n15 Wall-balls","judge":"Andrew Ridge","affiliate":"CrossFit Fierce Spirit"},"video":0},{"workoutrank":"29123","workoutresult":"--","scoreidentifier":"--","scoredisplay":"0","scoredetails":null,"video":"--"}]},{"userid":"802056","name":"Charles Rowley","regionid":"7","affiliateid":"0","divisionid":"5","highlight":0,"age":52,"region":"Europe","height":"5'10\"","weight":"69 kg","profilepic":"https:\/\/profilepicsbucket.crossfit.com\/pukie.png","overallrank":"31760","overallscore":"143384","affiliate":"","division":1,"scores":[{"workoutrank":"31709","workoutresult":"--","scoreidentifier":"4d59db9a91cf9e056dfb","scoredisplay":"15:52 - s","scoredetails":{"time":952,"breakdown":"225 reps"},"video":"1"},{"workoutrank":"29174","workoutresult":"--","scoreidentifier":"ef3c576d38099abd4693","scoredisplay":"171 reps - s","scoredetails":{"time":720,"breakdown":"5 Rounds\n5-ft lunges\n"},"video":"1"},{"workoutrank":"26857","workoutresult":"--","scoreidentifier":"243cc534c9485a3b4af0","scoredisplay":"117 reps - s","scoredetails":{"time":717,"breakdown":"9 Rounds\n9 Pull-ups"},"video":"1"},{"workoutrank":"28766","workoutresult":"--","scoreidentifier":"342c5b9e0d14bc802a48","scoredisplay":"201 reps - s","scoredetails":{"time":657,"breakdown":"55 Deadlifts\n55 Wall-balls\n55 Calories\n36 Push-ups"},"video":"1"},{"workoutrank":"26878","workoutresult":"--","scoreidentifier":"0ee3c34e94a8ffad2df9","scoredisplay":"13:33 - s","scoredetails":{"time":813,"breakdown":"440 reps"},"video":"1"}]},{"userid":"832235","name":"Eddie EscaDo","regionid":"7","affiliateid":"12625","divisionid":"12","highlight":0,"age":41,"region":"Europe","height":"","weight":"","profilepic":"https:\/\/profilepicsbucket.crossfit.com\/pukie.png","overallrank":"31761","overallscore":"143398","affiliate":"","division":1,"scores":[{"workoutrank":"25489","workoutresult":"--","scoreidentifier":"e718c35914246063c34e","scoredisplay":"181 reps","scoredetails":{"time":1068,"breakdown":"10 DB Snatches\n15 Burpees\n20 DB Snatches\n15 Burpees\n30 DB Snatches\n15 Burpees\n40 DB Snatches\n15 Burpees\n21 DB Snatches\n\nJudged by Dominique Bree\nat CrossFit Gladbeck"},"video":"0"},{"workoutrank":"24600","workoutresult":"--","scoreidentifier":"3ff959f2e0aa4b7af665","scoredisplay":"78 reps","scoredetails":{"time":511,"breakdown":"2 Rounds\n50-ft lunges\n","judge":"Tim Schur","affiliate":"CrossFit Gladbeck"},"video":0},{"workoutrank":"32418","workoutresult":"--","scoreidentifier":"--","scoredisplay":"0","scoredetails":null,"video":"--"},{"workoutrank":"31768","workoutresult":"--","scoreidentifier":"--","scoredisplay":"0","scoredetails":null,"video":"--"},{"workoutrank":"29123","workoutresult":"--","scoreidentifier":"--","scoredisplay":"0","scoredetails":null,"video":"--"}]},{"userid":"993115","name":"Jonathan Yenes","regionid":"7","affiliateid":"17715","divisionid":"1","highlight":0,"age":28,"region":"Europe","height":"176 cm","weight":"73 kg","profilepic":"https:\/\/profilepicsbucket.crossfit.com\/pukie.png","overallrank":"31762","overallscore":"143410","affiliate":"","division":1,"scores":[{"workoutrank":"21649","workoutresult":"--","scoreidentifier":"b702e6aed4678fa2c1e3","scoredisplay":"201 reps","scoredetails":{"time":1200,"breakdown":"10 DB Snatches\n15 Burpees\n20 DB Snatches\n15 Burpees\n30 DB Snatches\n15 Burpees\n40 DB Snatches\n15 Burpees\n41 DB Snatches\n\nJudged by Asier Calvo\nat CrossFit Urquijo"},"video":"0"},{"workoutrank":"28452","workoutresult":"--","scoreidentifier":"813a897c6302610387cd","scoredisplay":"192 reps - s","scoredetails":{"time":654,"breakdown":"5 Rounds\n50-ft lunges\n12 Knee-raises\n","judge":"Asier Calvo","affiliate":"CrossFit Urquijo"},"video":0},{"workoutrank":"32418","workoutresult":"--","scoreidentifier":"--","scoredisplay":"0","scoredetails":null,"video":"--"},{"workoutrank":"31768","workoutresult":"--","scoreidentifier":"--","scoredisplay":"0","scoredetails":null,"video":"--"},{"workoutrank":"29123","workoutresult":"--","scoreidentifier":"--","scoredisplay":"0","scoredetails":null,"video":"--"}]},{"userid":"941325","name":"Beno\u00eet Maury","regionid":"7","affiliateid":"11754","divisionid":"18","highlight":0,"age":39,"region":"Europe","height":"","weight":"","profilepic":"https:\/\/profilepicsbucket.crossfit.com\/pukie.png","overallrank":"31763","overallscore":"143413","affiliate":"","division":1,"scores":[{"workoutrank":"32814","workoutresult":"--","scoreidentifier":"56c730b066df1fe535c6","scoredisplay":"17:18 - s","scoredetails":{"time":1038,"breakdown":"225 reps\nJudged by Antonio Cima\nat CrossFit Montpellier"},"video":"0"},{"workoutrank":"29793","workoutresult":"--","scoreidentifier":"e3d73c7d585c73636152","scoredisplay":"158 reps - s","scoredetails":{"time":650,"breakdown":"4 Rounds\n50-ft lunges\n12 Knee-raises\n","judge":"Laurent Merle","affiliate":"CrossFit Castelnau le Lez"},"video":0},{"workoutrank":"28460","workoutresult":"--","scoreidentifier":"328ed3c9e49f2bb7647b","scoredisplay":"93 reps - s","scoredetails":{"time":446,"breakdown":"7 Rounds\n8 Pull-ups\n1 Snatches","judge":"Boit Julien","affiliate":"CrossFit Castelnau le Lez"},"video":0},{"workoutrank":"27572","workoutresult":"--","scoreidentifier":"4db434722d2628e0afa9","scoredisplay":"217 reps - s","scoredetails":{"time":576,"breakdown":"55 Deadlifts\n55 Wall-balls\n55 Calories\n52 Push-ups","judge":"Laurent Merle","affiliate":"CrossFit Castelnau le Lez"},"video":0},{"workoutrank":"24774","workoutresult":"--","scoreidentifier":"51f71ecd9047c1c5db83","scoredisplay":"10:47 - s","scoredetails":{"time":647,"breakdown":"440 reps","judge":"Vanina Potiron","affiliate":"CrossFit Castelnau le Lez"},"video":0}]},{"userid":"725517","name":"Bala Ambigapathy","regionid":"7","affiliateid":"13348","divisionid":"3","highlight":0,"age":46,"region":"Europe","height":"168 cm","weight":"69 kg","profilepic":"https:\/\/profilepicsbucket.crossfit.com\/pukie.png","overallrank":"31764","overallscore":"143419","affiliate":"","division":1,"scores":[{"workoutrank":"35688","workoutresult":"--","scoreidentifier":"3b2479c48089acb383b6","scoredisplay":"215 reps - s","scoredetails":{"time":935,"breakdown":"10 DB Snatches\n15 Burpees\n20 DB Snatches\n15 Burpees\n30 DB Snatches\n15 Burpees\n40 DB Snatches\n15 Burpees\n50 DB Snatches\n5 Burpees\nJudged by Leandro Liberal\nat CrossFit Venoge"},"video":"0"},{"workoutrank":"31372","workoutresult":"--","scoreidentifier":"9ba3a550f62214ac9e2d","scoredisplay":"129 reps - s","scoredetails":{"time":559,"breakdown":"3 Rounds\n50-ft lunges\n16 Pull-ups\n1 Power cleans\n","judge":"Yassin Ben Saida","affiliate":"CrossFit Venoge"},"video":0},{"workoutrank":"30218","workoutresult":"--","scoreidentifier":"7dbf5152bd735ce1ff90","scoredisplay":"67 reps - s","scoredetails":{"time":260,"breakdown":"5 Rounds\n7 Pull-ups","judge":"Yassin Ben Saida","affiliate":"CrossFit Venoge"},"video":0},{"workoutrank":"28092","workoutresult":"--","scoreidentifier":"699c9d629690d3d2218f","scoredisplay":"209 reps - s","scoredetails":{"time":668,"breakdown":"55 Deadlifts\n55 Wall-balls\n55 Calories\n44 Push-ups","judge":"Yassin Ben Saida","affiliate":"CrossFit Venoge"},"video":0},{"workoutrank":"18049","workoutresult":"--","scoreidentifier":"d8783c971b4bd16101e4","scoredisplay":"29:11","scoredetails":{"time":1751,"breakdown":"440 reps","judge":"Yassin Ben Saida","affiliate":"CrossFit Venoge"},"video":0}]},{"userid":"1025073","name":"Cristian Breveglieri","regionid":"7","affiliateid":"17278","divisionid":"12","highlight":0,"age":41,"region":"Europe","height":"","weight":"","profilepic":"https:\/\/profilepicsbucket.crossfit.com\/34b2e-P1025073_1-184.jpg","overallrank":"31765","overallscore":"143420","affiliate":"","division":1,"scores":[{"workoutrank":"33678","workoutresult":"--","scoreidentifier":"62e1fa50f382339ba2a5","scoredisplay":"18:19 - s","scoredetails":{"time":1099,"breakdown":"225 reps\nJudged by Roberto Ventura\nat CrossFit Zola Predosa"},"video":"0"},{"workoutrank":"29225","workoutresult":"--","scoreidentifier":"e31472f8ed36abdd74ab","scoredisplay":"170 reps - s","scoredetails":{"time":706,"breakdown":"5 Rounds\n0-ft lunges\n","judge":"Roberto Ventura","affiliate":"CrossFit Zola Predosa"},"video":0},{"workoutrank":"29186","workoutresult":"--","scoreidentifier":"92ec08597766f7f0de98","scoredisplay":"80 reps - s","scoredetails":{"time":470,"breakdown":"6 Rounds\n8 Pull-ups","judge":"Roberto Ventura","affiliate":"CrossFit Zola Predosa"},"video":0},{"workoutrank":"27421","workoutresult":"--","scoreidentifier":"1349384883e1d42dd3be","scoredisplay":"220 reps - s","scoredetails":{"time":780,"breakdown":"1 Round\n0 Deadlifts","judge":"Roberto Ventura","affiliate":"CrossFit Zola Predosa"},"video":0},{"workoutrank":"23910","workoutresult":"--","scoreidentifier":"ee837b968bc1fddb567f","scoredisplay":"9:50 - s","scoredetails":{"time":590,"breakdown":"440 reps","judge":"Roberto Ventura","affiliate":"CrossFit Zola Predosa"},"video":0}]},{"userid":"959118","name":"Ilias Tsimpoulis","regionid":"7","affiliateid":"8140","divisionid":"18","highlight":0,"age":39,"region":"Europe","height":"181 cm","weight":"80 kg","profilepic":"https:\/\/profilepicsbucket.crossfit.com\/2dcbc-P959118_1-184.jpg","overallrank":"31766","overallscore":"143427","affiliate":"","division":1,"scores":[{"workoutrank":"35747","workoutresult":"--","scoreidentifier":"1c65e195eb9c69d84419","scoredisplay":"214 reps - s","scoredetails":{"time":939,"breakdown":"10 DB Snatches\n15 Burpees\n20 DB Snatches\n15 Burpees\n30 DB Snatches\n15 Burpees\n40 DB Snatches\n15 Burpees\n50 DB Snatches\n4 Burpees\nJudged by Sarah Klitzke\nat CrossFit Joule"},"video":"0"},{"workoutrank":"26304","workoutresult":"--","scoreidentifier":"c47349e81372a7147cb6","scoredisplay":"73 reps","scoredetails":{"time":655,"breakdown":"2 Rounds\n25-ft lunges\n","judge":"Markus Schuster","affiliate":"CrossFit Joule"},"video":0},{"workoutrank":"23473","workoutresult":"--","scoreidentifier":"ca85a46fb7b915a74c5a","scoredisplay":"19 reps","scoredetails":{"time":1440,"breakdown":"1 Rounds\n6 Pull-ups\n1 Snatches","judge":"Sarah Klitzke","affiliate":"CrossFit Joule"},"video":0},{"workoutrank":"30778","workoutresult":"--","scoreidentifier":"8be0d31167cad54243f6","scoredisplay":"170 reps - s","scoredetails":{"time":768,"breakdown":"55 Deadlifts\n55 Wall-balls\n55 Calories\n5 Push-ups","judge":"Markus Schuster","affiliate":"CrossFit Joule"},"video":0},{"workoutrank":"27125","workoutresult":"--","scoreidentifier":"c4f28c320ecd78e9b021","scoredisplay":"13:58 - s","scoredetails":{"time":838,"breakdown":"440 reps","judge":"Markus Schuster","affiliate":"CrossFit Joule"},"video":0}]},{"userid":"739494","name":"Andrew Lang","regionid":"7","affiliateid":"13796","divisionid":"1","highlight":0,"age":30,"region":"Europe","height":"6'0\"","weight":"95 kg","profilepic":"https:\/\/profilepicsbucket.crossfit.com\/pukie.png","overallrank":"31767","overallscore":"143429","affiliate":"","division":1,"scores":[{"workoutrank":"21635","workoutresult":"--","scoreidentifier":"f9302489deef4134b901","scoredisplay":"201 reps","scoredetails":{"time":1007,"breakdown":"10 DB Snatches\n15 Burpees\n20 DB Snatches\n15 Burpees\n30 DB Snatches\n15 Burpees\n40 DB Snatches\n15 Burpees\n41 DB Snatches\n\nJudged by \u200eCaspar Chittenden\u200e\nat 3 Aces CrossFit"},"video":"0"},{"workoutrank":"31636","workoutresult":"--","scoreidentifier":"c936ff18a0e764028c8a","scoredisplay":"125 reps - s","scoredetails":{"time":497,"breakdown":"3 Rounds\n50-ft lunges\n13 Pull-ups\n","judge":"Caspar Chittenden","affiliate":"3 Aces CrossFit"},"video":0},{"workoutrank":"32418","workoutresult":"--","scoreidentifier":"--","scoredisplay":"0","scoredetails":null,"video":"--"},{"workoutrank":"31768","workoutresult":"--","scoreidentifier":"--","scoredisplay":"0","scoredetails":null,"video":"--"},{"workoutrank":"25972","workoutresult":"--","scoreidentifier":"e1171bb0ce0100f49bff","scoredisplay":"12:14 - s","scoredetails":{"time":734,"breakdown":"440 reps","judge":"Caspar Chittenden","affiliate":"3 Aces CrossFit"},"video":0}]},{"userid":"692528","name":"Dylan Kerrigan","regionid":"7","affiliateid":"17083","divisionid":"1","highlight":0,"age":30,"region":"Europe","height":"","weight":"","profilepic":"https:\/\/profilepicsbucket.crossfit.com\/pukie.png","overallrank":"31768","overallscore":"143431","affiliate":"","division":1,"scores":[{"workoutrank":"30225","workoutresult":"--","scoreidentifier":"612ab7c7048cee19d1dc","scoredisplay":"105 reps","scoredetails":{"time":650,"breakdown":"10 DB Snatches\n15 Burpees\n20 DB Snatches\n15 Burpees\n30 DB Snatches\n15 Burpees\n\nJudged by Patrick Jack\nat CrossFit Evolving Kilburn"},"video":"0"},{"workoutrank":"34748","workoutresult":"--","scoreidentifier":"--","scoredisplay":"0","scoredetails":null,"video":"--"},{"workoutrank":"23576","workoutresult":"--","scoreidentifier":"a5c43d4e609cab9e2a22","scoredisplay":"18 reps","scoredetails":{"time":1440,"breakdown":"1 Rounds\n6 Pull-ups","judge":"Patrick Jack","affiliate":"CrossFit Evolving Kilburn"},"video":0},{"workoutrank":"25759","workoutresult":"--","scoreidentifier":"084e42a31a24ab0ec3ce","scoredisplay":"34 reps","scoredetails":{"time":780,"breakdown":"34 Deadlifts","judge":"Patrick Jack","affiliate":"CrossFit Evolving Kilburn"},"video":0},{"workoutrank":"29123","workoutresult":"--","scoreidentifier":"--","scoredisplay":"0","scoredetails":null,"video":"--"}]},{"userid":"949925","name":"Boissier Jh","regionid":"7","affiliateid":"12720","divisionid":"1","highlight":0,"age":34,"region":"Europe","height":"","weight":"","profilepic":"https:\/\/profilepicsbucket.crossfit.com\/90cd2-P949925_1-184.jpg","overallrank":"31769","overallscore":"143432","affiliate":"","division":1,"scores":[{"workoutrank":"29506","workoutresult":"--","scoreidentifier":"76ddacdfb4c5a7e45b77","scoredisplay":"146 reps","scoredetails":{"time":862,"breakdown":"10 DB Snatches\n15 Burpees\n20 DB Snatches\n15 Burpees\n30 DB Snatches\n15 Burpees\n40 DB Snatches\n1 Burpees\n\nJudged by Thomas Lacombe\nat CrossFit Agen"},"video":"0"},{"workoutrank":"29606","workoutresult":"--","scoreidentifier":"13a09ebd4d20f2e9d369","scoredisplay":"162 reps - s","scoredetails":{"time":600,"breakdown":"4 Rounds\n50-ft lunges\n16 Knee-raises\n","judge":"Thomas Lacombe","affiliate":"CrossFit Agen"},"video":0},{"workoutrank":"28729","workoutresult":"--","scoreidentifier":"4937527ff590774bff7e","scoredisplay":"92 reps - s","scoredetails":{"time":474,"breakdown":"7 Rounds\n8 Pull-ups","judge":"Thomas Lacombe","affiliate":"CrossFit Agen"},"video":0},{"workoutrank":"28414","workoutresult":"--","scoreidentifier":"ba1f1d3bb2e32c8eb7cc","scoredisplay":"205 reps - s","scoredetails":{"time":608,"breakdown":"55 Deadlifts\n55 Wall-balls\n55 Calories\n40 Push-ups","judge":"Thomas Lacombe","affiliate":"CrossFit Agen"},"video":0},{"workoutrank":"27177","workoutresult":"--","scoreidentifier":"49a9a62013089974129f","scoredisplay":"14:04 - s","scoredetails":{"time":844,"breakdown":"440 reps","judge":"Kevin Bidart","affiliate":"CrossFit Agen"},"video":0}]},{"userid":"959019","name":"Emilio Lozana","regionid":"7","affiliateid":"11175","divisionid":"3","highlight":0,"age":47,"region":"Europe","height":"","weight":"72 kg","profilepic":"https:\/\/profilepicsbucket.crossfit.com\/50c0e-P959019_1-184.jpg","overallrank":"31770","overallscore":"143433","affiliate":"","division":1,"scores":[{"workoutrank":"35220","workoutresult":"--","scoreidentifier":"4051a269c41a28290194","scoredisplay":"223 reps - s","scoredetails":{"time":847,"breakdown":"10 DB Snatches\n15 Burpees\n20 DB Snatches\n15 Burpees\n30 DB Snatches\n15 Burpees\n40 DB Snatches\n15 Burpees\n50 DB Snatches\n13 Burpees\nJudged by Oscar Zas mediero\nat CrossFit Aviles"},"video":"0"},{"workoutrank":"27027","workoutresult":"--","scoreidentifier":"7d7c1b022c69dc98643c","scoredisplay":"55 reps","scoredetails":{"time":291,"breakdown":"1 Rounds\n50-ft lunges\n11 T2B\n","judge":"Oscar Zas mediero","affiliate":"CrossFit Aviles"},"video":0},{"workoutrank":"24126","workoutresult":"--","scoreidentifier":"eae5a55a7e40ee37868b","scoredisplay":"6 reps","scoredetails":{"time":1440,"breakdown":"0 Rounds\n6 Pull-ups","judge":"Oscar Zas mediero","affiliate":"CrossFit Aviles"},"video":0},{"workoutrank":"30483","workoutresult":"--","scoreidentifier":"f3827fb3890a6259a19f","scoredisplay":"178 reps - s","scoredetails":{"time":749,"breakdown":"178 reps","judge":"Jose Garcia Morado","affiliate":"CrossFit Aviles"},"video":0},{"workoutrank":"26577","workoutresult":"--","scoreidentifier":"4edce22caff5cea85355","scoredisplay":"13:05 - s","scoredetails":{"time":785,"breakdown":"440 reps","judge":"Jose Garcia Morado","affiliate":"CrossFit Aviles"},"video":0}]},{"userid":"903385","name":"Davide Giusti","regionid":"7","affiliateid":"11570","divisionid":"12","highlight":0,"age":40,"region":"Europe","height":"178 cm","weight":"90 kg","profilepic":"https:\/\/profilepicsbucket.crossfit.com\/32168-P903385_1-184.jpg","overallrank":"31771","overallscore":"143436","affiliate":"","division":1,"scores":[{"workoutrank":"37098","workoutresult":"--","scoreidentifier":"--","scoredisplay":"0","scoredetails":null,"video":"--"},{"workoutrank":"29078","workoutresult":"--","scoreidentifier":"a7bcc9bfabdb76e47031","scoredisplay":"173 reps - s","scoredetails":{"time":720,"breakdown":"5 Rounds\n15-ft lunges\n","judge":"Paolo Vanin","affiliate":"CrossFit Fides"},"video":0},{"workoutrank":"25421","workoutresult":"--","scoreidentifier":"e1686db48d8a16c347fa","scoredisplay":"155 reps - s","scoredetails":{"time":906,"breakdown":"12 Rounds\n10 Pull-ups\n1 Snatches","judge":"Samuel Baiano","affiliate":"CrossFit Fides"},"video":0},{"workoutrank":"26321","workoutresult":"--","scoreidentifier":"7d32b8634c7927a5e88b","scoredisplay":"252 reps - s","scoredetails":{"time":510,"breakdown":"1 Round\n32 Deadlifts","judge":"Paolo Vanin","affiliate":"CrossFit Fides"},"video":0},{"workoutrank":"25518","workoutresult":"--","scoreidentifier":"438f5ceb9b305a1cb1db","scoredisplay":"11:38 - s","scoredetails":{"time":698,"breakdown":"440 reps","judge":"Paolo Vanin","affiliate":"CrossFit Fides"},"video":0}]},{"userid":"985722","name":"Matthew Piovan","regionid":"7","affiliateid":"1359","divisionid":"1","highlight":0,"age":34,"region":"Europe","height":"194 cm","weight":"76 kg","profilepic":"https:\/\/profilepicsbucket.crossfit.com\/pukie.png","overallrank":"31772","overallscore":"143446","affiliate":"","division":1,"scores":[{"workoutrank":"32906","workoutresult":"--","scoreidentifier":"8f14f856c2ce8d071c39","scoredisplay":"17:24 - s","scoredetails":{"time":1044,"breakdown":"225 reps\nJudged by Martyn Lever\nat CrossFit Bournemouth"},"video":"0"},{"workoutrank":"28962","workoutresult":"--","scoreidentifier":"5cf440c4a49353328133","scoredisplay":"175 reps - s","scoredetails":{"time":720,"breakdown":"5 Rounds\n25-ft lunges\n","judge":"Martyn Lever","affiliate":"CrossFit Bournemouth"},"video":0},{"workoutrank":"26815","workoutresult":"--","scoreidentifier":"0c971766c5f69d5bf411","scoredisplay":"117 reps - s","scoredetails":{"time":708,"breakdown":"9 Rounds\n9 Pull-ups","judge":"Martyn Lever","affiliate":"CrossFit Bournemouth"},"video":0},{"workoutrank":"27726","workoutresult":"--","scoreidentifier":"4bd319f9343d26b742f3","scoredisplay":"214 reps - s","scoredetails":{"time":549,"breakdown":"55 Deadlifts\n55 Wall-balls\n55 Calories\n49 Push-ups","judge":"Martyn Lever","affiliate":"CrossFit Bournemouth"},"video":0},{"workoutrank":"27037","workoutresult":"--","scoreidentifier":"a80bdcc1da9bc5e5587b","scoredisplay":"13:48 - s","scoredetails":{"time":828,"breakdown":"440 reps","judge":"Martyn Lever","affiliate":"CrossFit Bournemouth"},"video":0}]},{"userid":"1050550","name":"Juha Salmenper\u00e4","regionid":"7","affiliateid":"10908","divisionid":"3","highlight":0,"age":47,"region":"Europe","height":"176 cm","weight":"78 lb","profilepic":"https:\/\/profilepicsbucket.crossfit.com\/pukie.png","overallrank":"31773","overallscore":"143447","affiliate":"","division":1,"scores":[{"workoutrank":"24677","workoutresult":"--","scoreidentifier":"0b614f4f15079802693f","scoredisplay":"186 reps","scoredetails":{"time":1070,"breakdown":"10 DB Snatches\n15 Burpees\n20 DB Snatches\n15 Burpees\n30 DB Snatches\n15 Burpees\n40 DB Snatches\n15 Burpees\n26 DB Snatches\n\nJudged by Marko Hakanen\nat CrossFit Kirkkonummi"},"video":"0"},{"workoutrank":"25461","workoutresult":"--","scoreidentifier":"baa924e3bc236eaa0f82","scoredisplay":"78 reps","scoredetails":{"time":595,"breakdown":"2 Rounds\n50-ft lunges\n","judge":"Micke Hakkarainen","affiliate":"CrossFit Kirkkonummi"},"video":0},{"workoutrank":"32418","workoutresult":"--","scoreidentifier":"--","scoredisplay":"0","scoredetails":null,"video":"--"},{"workoutrank":"31768","workoutresult":"--","scoreidentifier":"--","scoredisplay":"0","scoredetails":null,"video":"--"},{"workoutrank":"29123","workoutresult":"--","scoreidentifier":"--","scoredisplay":"0","scoredetails":null,"video":"--"}]},{"userid":"505572","name":"Leroy Holwerda","regionid":"7","affiliateid":"7799","divisionid":"12","highlight":0,"age":41,"region":"Europe","height":"174 cm","weight":"82 kg","profilepic":"https:\/\/profilepicsbucket.crossfit.com\/92234-P505572_1-184.jpg","overallrank":"31774","overallscore":"143454","affiliate":"","division":1,"scores":[{"workoutrank":"37098","workoutresult":"--","scoreidentifier":"--","scoredisplay":"0","scoredetails":null,"video":"--"},{"workoutrank":"31973","workoutresult":"--","scoreidentifier":"1de83a6ba1c544c2774d","scoredisplay":"121 reps - s","scoredetails":{"time":541,"breakdown":"3 Rounds\n50-ft lunges\n9 Pull-ups\n","judge":"Haroen Maree","affiliate":"CrossFit Zoetermeer"},"video":0},{"workoutrank":"20607","workoutresult":"--","scoreidentifier":"1456a43846d45fe79230","scoredisplay":"43 reps","scoredetails":{"time":1440,"breakdown":"3 Rounds\n7 Pull-ups","judge":"Haroen Maree","affiliate":"CrossFit Zoetermeer"},"video":0},{"workoutrank":"24653","workoutresult":"--","scoreidentifier":"0860300ac7ea6ebbe286","scoredisplay":"96 reps","scoredetails":{"time":780,"breakdown":"55 Deadlifts\n41 Wall-balls","judge":"Haroen Maree","affiliate":"CrossFit Zoetermeer"},"video":0},{"workoutrank":"29123","workoutresult":"--","scoreidentifier":"--","scoredisplay":"0","scoredetails":null,"video":"--"}]},{"userid":"695438","name":"Stephen Brady","regionid":"7","affiliateid":"10200","divisionid":"12","highlight":0,"age":42,"region":"Europe","height":"6'3\"","weight":"100 kg","profilepic":"https:\/\/profilepicsbucket.crossfit.com\/a7898-P695438_1-184.jpg","overallrank":"31775","overallscore":"143460","affiliate":"","division":1,"scores":[{"workoutrank":"32524","workoutresult":"--","scoreidentifier":"ee0c6fa91bafa04c164d","scoredisplay":"16:56 - s","scoredetails":{"time":1016,"breakdown":"225 reps\nJudged by Mark Toner\nat CrossFit Infected"},"video":"0"},{"workoutrank":"32654","workoutresult":"--","scoreidentifier":"fc94f84f2192972d6d86","scoredisplay":"114 reps - s","scoredetails":{"time":654,"breakdown":"3 Rounds\n50-ft lunges\n2 Pull-ups\n","judge":"Mark Toner","affiliate":"CrossFit Infected"},"video":0},{"workoutrank":"27156","workoutresult":"--","scoreidentifier":"21dc5cba4d8dd8b12769","scoredisplay":"106 reps - s","scoredetails":{"time":417,"breakdown":"8 Rounds\n8 Pull-ups\n2 Snatches","judge":"Mark Toner","affiliate":"CrossFit Infected"},"video":0},{"workoutrank":"27483","workoutresult":"--","scoreidentifier":"4e72cada9315f373a583","scoredisplay":"219 reps - s","scoredetails":{"time":571,"breakdown":"55 Deadlifts\n55 Wall-balls\n55 Calories\n54 Push-ups","judge":"Mark Toner","affiliate":"CrossFit Infected"},"video":0},{"workoutrank":"23643","workoutresult":"--","scoreidentifier":"c9d91e5e10424f9b4ee3","scoredisplay":"9:35 - s","scoredetails":{"time":575,"breakdown":"440 reps","judge":"Mark Toner","affiliate":"CrossFit Infected"},"video":0}]},{"userid":"926064","name":"Linus Grudd","regionid":"7","affiliateid":"0","divisionid":"1","highlight":0,"age":26,"region":"Europe","height":"184 cm","weight":"94 kg","profilepic":"https:\/\/profilepicsbucket.crossfit.com\/d2b37-P926064_2-184.jpg","overallrank":"31776","overallscore":"143462","affiliate":"","division":1,"scores":[{"workoutrank":"15405","workoutresult":"--","scoreidentifier":"549e67a402f9510cf9d3","scoredisplay":"19:55","scoredetails":{"time":1195,"breakdown":"225 reps\nJudged by Erik Gustavsson\nat CrossFit Kungsholmen"},"video":"0"},{"workoutrank":"34748","workoutresult":"--","scoreidentifier":"--","scoredisplay":"0","scoredetails":null,"video":"--"},{"workoutrank":"32418","workoutresult":"--","scoreidentifier":"--","scoredisplay":"0","scoredetails":null,"video":"--"},{"workoutrank":"31768","workoutresult":"--","scoreidentifier":"--","scoredisplay":"0","scoredetails":null,"video":"--"},{"workoutrank":"29123","workoutresult":"--","scoreidentifier":"--","scoredisplay":"0","scoredetails":null,"video":"--"}]},{"userid":"948549","name":"Jordan Besnard","regionid":"7","affiliateid":"11336","divisionid":"1","highlight":0,"age":22,"region":"Europe","height":"175 cm","weight":"78 kg","profilepic":"https:\/\/profilepicsbucket.crossfit.com\/pukie.png","overallrank":"31776","overallscore":"143462","affiliate":"","division":1,"scores":[{"workoutrank":"15405","workoutresult":"--","scoreidentifier":"7ca585341b629d8db551","scoredisplay":"19:55","scoredetails":{"time":1195,"breakdown":"225 reps\nJudged by Sabrina Nunes\nat 1789 CrossFit"},"video":"0"},{"workoutrank":"34748","workoutresult":"--","scoreidentifier":"--","scoredisplay":"0","scoredetails":null,"video":"--"},{"workoutrank":"32418","workoutresult":"--","scoreidentifier":"--","scoredisplay":"0","scoredetails":null,"video":"--"},{"workoutrank":"31768","workoutresult":"--","scoreidentifier":"--","scoredisplay":"0","scoredetails":null,"video":"--"},{"workoutrank":"29123","workoutresult":"--","scoreidentifier":"--","scoredisplay":"0","scoredetails":null,"video":"--"}]},{"userid":"466401","name":"Hyeon-Won Song","regionid":"7","affiliateid":"15919","divisionid":"18","highlight":0,"age":35,"region":"Europe","height":"","weight":"","profilepic":"https:\/\/profilepicsbucket.crossfit.com\/pukie.png","overallrank":"31776","overallscore":"143462","affiliate":"","division":1,"scores":[{"workoutrank":"15405","workoutresult":"--","scoreidentifier":"4699402af575224cf6cb","scoredisplay":"19:55","scoredetails":{"time":1195,"breakdown":"225 reps\nJudged by Isabelle Derond\nat Bowery CrossFit"},"video":"0"},{"workoutrank":"34748","workoutresult":"--","scoreidentifier":"--","scoredisplay":"0","scoredetails":null,"video":"--"},{"workoutrank":"32418","workoutresult":"--","scoreidentifier":"--","scoredisplay":"0","scoredetails":null,"video":"--"},{"workoutrank":"31768","workoutresult":"--","scoreidentifier":"--","scoredisplay":"0","scoredetails":null,"video":"--"},{"workoutrank":"29123","workoutresult":"--","scoreidentifier":"--","scoredisplay":"0","scoredetails":null,"video":"--"}]},{"userid":"1032153","name":"Richard Buzasi","regionid":"7","affiliateid":"12735","divisionid":"1","highlight":0,"age":26,"region":"Europe","height":"174 cm","weight":"90 kg","profilepic":"https:\/\/profilepicsbucket.crossfit.com\/pukie.png","overallrank":"31776","overallscore":"143462","affiliate":"","division":1,"scores":[{"workoutrank":"15405","workoutresult":"--","scoreidentifier":"737fb821f44acadb8544","scoredisplay":"19:55","scoredetails":{"time":1195,"breakdown":"225 reps\nJudged by Soti Zsolt\nat CrossFit BBros"},"video":"0"},{"workoutrank":"34748","workoutresult":"--","scoreidentifier":"--","scoredisplay":"0","scoredetails":null,"video":"--"},{"workoutrank":"32418","workoutresult":"--","scoreidentifier":"--","scoredisplay":"0","scoredetails":null,"video":"--"},{"workoutrank":"31768","workoutresult":"--","scoreidentifier":"--","scoredisplay":"0","scoredetails":null,"video":"--"},{"workoutrank":"29123","workoutresult":"--","scoreidentifier":"--","scoredisplay":"0","scoredetails":null,"video":"--"}]},{"userid":"1101460","name":"Shane Roche","regionid":"7","affiliateid":"18730","divisionid":"12","highlight":0,"age":40,"region":"Europe","height":"","weight":"178 lb","profilepic":"https:\/\/profilepicsbucket.crossfit.com\/pukie.png","overallrank":"31776","overallscore":"143462","affiliate":"","division":1,"scores":[{"workoutrank":"15405","workoutresult":"--","scoreidentifier":"7d664bf370dc79bc2d0a","scoredisplay":"19:55","scoredetails":{"time":1195,"breakdown":"225 reps\nJudged by Tony Sullivan\nat CrossFit Laochra"},"video":"0"},{"workoutrank":"34748","workoutresult":"--","scoreidentifier":"--","scoredisplay":"0","scoredetails":null,"video":"--"},{"workoutrank":"32418","workoutresult":"--","scoreidentifier":"--","scoredisplay":"0","scoredetails":null,"video":"--"},{"workoutrank":"31768","workoutresult":"--","scoreidentifier":"--","scoredisplay":"0","scoredetails":null,"video":"--"},{"workoutrank":"29123","workoutresult":"--","scoreidentifier":"--","scoredisplay":"0","scoredetails":null,"video":"--"}]},{"userid":"493254","name":"Sam Unwin","regionid":"7","affiliateid":"7492","divisionid":"1","highlight":0,"age":28,"region":"Europe","height":"174 cm","weight":"88 kg","profilepic":"https:\/\/profilepicsbucket.crossfit.com\/2ddec-P493254_1-184.jpg","overallrank":"31776","overallscore":"143462","affiliate":"","division":1,"scores":[{"workoutrank":"29433","workoutresult":"--","scoreidentifier":"60f9aeebed6e70e48b0a","scoredisplay":"147 reps","scoredetails":{"time":872,"breakdown":"10 DB Snatches\n15 Burpees\n20 DB Snatches\n15 Burpees\n30 DB Snatches\n15 Burpees\n40 DB Snatches\n2 Burpees\n\nJudged by Christopher lawler\nat CrossFit Wirral"},"video":"0"},{"workoutrank":"34748","workoutresult":"--","scoreidentifier":"--","scoredisplay":"0","scoredetails":null,"video":"--"},{"workoutrank":"26400","workoutresult":"--","scoreidentifier":"589a94eba77e46761faa","scoredisplay":"129 reps - s","scoredetails":{"time":680,"breakdown":"10 Rounds\n9 Pull-ups","judge":"Christopher Lawler","affiliate":"CrossFit Wirral"},"video":0},{"workoutrank":"23758","workoutresult":"--","scoreidentifier":"ee44a9df7e8c20077ed7","scoredisplay":"113 reps","scoredetails":{"time":751,"breakdown":"55 Deadlifts\n55 Wall-balls\n3 Calories","judge":"Chris Lawler","affiliate":"CrossFit Wirral"},"video":0},{"workoutrank":"29123","workoutresult":"--","scoreidentifier":"--","scoredisplay":"0","scoredetails":null,"video":"--"}]},{"userid":"951736","name":"Dami\u00e0 Rodriguez","regionid":"7","affiliateid":"13492","divisionid":"5","highlight":0,"age":53,"region":"Europe","height":"170 cm","weight":"66 kg","profilepic":"https:\/\/profilepicsbucket.crossfit.com\/7cf9b-P951736_3-184.jpg","overallrank":"31782","overallscore":"143466","affiliate":"","division":1,"scores":[{"workoutrank":"31070","workoutresult":"--","scoreidentifier":"2e735d6d6ac630a6536f","scoredisplay":"14:44 - s","scoredetails":{"time":884,"breakdown":"225 reps\nJudged by Cristina Martinez Jimenez\nat CrossFit Poblenou"},"video":"0"},{"workoutrank":"31356","workoutresult":"--","scoreidentifier":"81881ce3dd0d32ae935c","scoredisplay":"129 reps - s","scoredetails":{"time":420,"breakdown":"3 Rounds\n50-ft lunges\n16 Pull-ups\n1 Power cleans\n","judge":"Cristina Martinez Jimenez","affiliate":"CrossFit Poblenou"},"video":0},{"workoutrank":"29869","workoutresult":"--","scoreidentifier":"2c5fb4c0975769e35eff","scoredisplay":"68 reps - s","scoredetails":{"time":150,"breakdown":"5 Rounds\n7 Pull-ups\n1 Snatches","judge":"Cristina Martinez Jimenez","affiliate":"CrossFit Poblenou"},"video":0},{"workoutrank":"27622","workoutresult":"--","scoreidentifier":"834d7c9d2de8ed4be60a","scoredisplay":"216 reps - s","scoredetails":{"time":602,"breakdown":"55 Deadlifts\n55 Wall-balls\n55 Calories\n51 Push-ups","judge":"Cristina Martinez Jimenez","affiliate":"CrossFit Poblenou"},"video":0},{"workoutrank":"23549","workoutresult":"--","scoreidentifier":"29b7ffc309ad83b56c4a","scoredisplay":"9:30 - s","scoredetails":{"time":570,"breakdown":"440 reps","judge":"Cristina Martinez Jimenez","affiliate":"CrossFit Poblenou"},"video":0}]},{"userid":"454454","name":"Ilya Karasev","regionid":"7","affiliateid":"17539","divisionid":"1","highlight":0,"age":27,"region":"Europe","height":"173 cm","weight":"70 kg","profilepic":"https:\/\/profilepicsbucket.crossfit.com\/ec0c3-P454454_1-184.jpg","overallrank":"31782","overallscore":"143466","affiliate":"","division":1,"scores":[{"workoutrank":"32659","workoutresult":"--","scoreidentifier":"0e8b62b4c1bfe539aef6","scoredisplay":"17:07 - s","scoredetails":{"time":1027,"breakdown":"225 reps\nJudged by Yakovleva Liudmila\nat Soyuz CrossFit"},"video":"0"},{"workoutrank":"29274","workoutresult":"--","scoreidentifier":"6d3f25d30cc481eab7f8","scoredisplay":"170 reps - s","scoredetails":{"time":716,"breakdown":"5 Rounds\n0-ft lunges\n","judge":"Lyudmila Yakovleva","affiliate":"Soyuz CrossFit"},"video":0},{"workoutrank":"27013","workoutresult":"--","scoreidentifier":"4f384c5e2e207bced5d7","scoredisplay":"107 reps - s","scoredetails":{"time":427,"breakdown":"8 Rounds\n8 Pull-ups\n3 Snatches","judge":"Lyudmila Yakovleva","affiliate":"Soyuz CrossFit"},"video":0},{"workoutrank":"29164","workoutresult":"--","scoreidentifier":"9d6682164155ea22202f","scoredisplay":"196 reps - s","scoredetails":{"time":624,"breakdown":"55 Deadlifts\n55 Wall-balls\n55 Calories\n31 Push-ups","judge":"Lyudmila Yakovleva","affiliate":"Soyuz CrossFit"},"video":0},{"workoutrank":"25356","workoutresult":"--","scoreidentifier":"a11470cb321752d784aa","scoredisplay":"11:26 - s","scoredetails":{"time":686,"breakdown":"440 reps","judge":"Lyudmila Yakovleva","affiliate":"Soyuz CrossFit"},"video":0}]},{"userid":"679166","name":"Karl Andrews","regionid":"7","affiliateid":"11072","divisionid":"1","highlight":0,"age":34,"region":"Europe","height":"","weight":"88 kg","profilepic":"https:\/\/profilepicsbucket.crossfit.com\/pukie.png","overallrank":"31782","overallscore":"143466","affiliate":"","division":1,"scores":[{"workoutrank":"29552","workoutresult":"--","scoreidentifier":"3e1da593b198b78f3688","scoredisplay":"145 reps","scoredetails":{"time":814,"breakdown":"10 DB Snatches\n15 Burpees\n20 DB Snatches\n15 Burpees\n30 DB Snatches\n15 Burpees\n40 DB Snatches\n\nJudged by Sam Baker\nat CrossFit Fearnaught"},"video":"0"},{"workoutrank":"27363","workoutresult":"--","scoreidentifier":"9200376ef36fd34bde6e","scoredisplay":"39 reps","scoredetails":{"time":660,"breakdown":"1 Rounds\n25-ft lunges\n","judge":"Helen Cross","affiliate":"CrossFit Fearnaught"},"video":0},{"workoutrank":"28756","workoutresult":"--","scoreidentifier":"cdce407c3b745c662c70","scoredisplay":"92 reps - s","scoredetails":{"time":479,"breakdown":"7 Rounds\n8 Pull-ups","judge":"Matt Nash","affiliate":"CrossFit Fearnaught"},"video":0},{"workoutrank":"31768","workoutresult":"--","scoreidentifier":"--","scoredisplay":"0","scoredetails":null,"video":"--"},{"workoutrank":"26027","workoutresult":"--","scoreidentifier":"60686f338472ae58211a","scoredisplay":"12:18 - s","scoredetails":{"time":738,"breakdown":"440 reps","judge":"Sam Baker","affiliate":"CrossFit Fearnaught"},"video":0}]},{"userid":"990137","name":"Marco Sestini","regionid":"7","affiliateid":"17084","divisionid":"12","highlight":0,"age":40,"region":"Europe","height":"170 cm","weight":"70 kg","profilepic":"https:\/\/profilepicsbucket.crossfit.com\/b2131-P990137_1-184.jpg","overallrank":"31785","overallscore":"143468","affiliate":"","division":1,"scores":[{"workoutrank":"34037","workoutresult":"--","scoreidentifier":"3b99d5232ff1549430e5","scoredisplay":"18:43 - s","scoredetails":{"time":1123,"breakdown":"225 reps\nJudged by Valentino Girotto\nat CrossFit 30027"},"video":"0"},{"workoutrank":"30513","workoutresult":"--","scoreidentifier":"faa4b57045aff13bb965","scoredisplay":"142 reps - s","scoredetails":{"time":693,"breakdown":"4 Rounds\n30-ft lunges\n","judge":"Enrico Gianello","affiliate":"CrossFit 30027"},"video":0},{"workoutrank":"26668","workoutresult":"--","scoreidentifier":"d9d7597c4f7b8781bb7f","scoredisplay":"118 reps - s","scoredetails":{"time":655,"breakdown":"9 Rounds\n9 Pull-ups\n1 Snatches","judge":"Valentino Girotto","affiliate":"CrossFit 30027"},"video":0},{"workoutrank":"27532","workoutresult":"--","scoreidentifier":"3f46c9218c1e8cf8fb9e","scoredisplay":"218 reps - s","scoredetails":{"time":586,"breakdown":"218 reps","judge":"Enrico Gianello","affiliate":"CrossFit 30027"},"video":0},{"workoutrank":"24718","workoutresult":"--","scoreidentifier":"7174a30b54253a7c2c73","scoredisplay":"10:44 - s","scoredetails":{"time":644,"breakdown":"440 reps","judge":"Valentino Girotto","affiliate":"CrossFit 30027"},"video":0}]},{"userid":"958286","name":"Derek Mawhinney","regionid":"7","affiliateid":"15417","divisionid":"18","highlight":0,"age":39,"region":"Europe","height":"","weight":"","profilepic":"https:\/\/profilepicsbucket.crossfit.com\/pukie.png","overallrank":"31786","overallscore":"143469","affiliate":"","division":1,"scores":[{"workoutrank":"33442","workoutresult":"--","scoreidentifier":"dccf711faf6cc1150449","scoredisplay":"18:00 - s","scoredetails":{"time":1080,"breakdown":"225 reps\nJudged by John McGeachy\nat CrossFit Larne"},"video":"0"},{"workoutrank":"19817","workoutresult":"--","scoreidentifier":"847b572f73105c7f3023","scoredisplay":"79 reps","scoredetails":{"time":550,"breakdown":"2 Rounds\n50-ft lunges\n1 Bar MU\n","judge":"John McGeachy","affiliate":"CrossFit Larne"},"video":0},{"workoutrank":"31407","workoutresult":"--","scoreidentifier":"684170ae5730ee408640","scoredisplay":"52 reps - s","scoredetails":{"time":350,"breakdown":"4 Rounds\n4 Pull-ups","judge":"John McGeachy","affiliate":"CrossFit Larne"},"video":0},{"workoutrank":"31373","workoutresult":"--","scoreidentifier":"73191e5e509e37232e07","scoredisplay":"146 reps - s","scoredetails":{"time":780,"breakdown":"55 Deadlifts\n55 Wall-balls\n36 Calories","judge":"John McGeachy","affiliate":"CrossFit Larne"},"video":0},{"workoutrank":"27430","workoutresult":"--","scoreidentifier":"dbcdea958ee88cc38c58","scoredisplay":"14:34 - s","scoredetails":{"time":874,"breakdown":"440 reps","judge":"John McGeachy","affiliate":"CrossFit Larne"},"video":0}]},{"userid":"695447","name":"Juuso Syv\u00e4luoma","regionid":"7","affiliateid":"3121","divisionid":"12","highlight":0,"age":41,"region":"Europe","height":"","weight":"","profilepic":"https:\/\/profilepicsbucket.crossfit.com\/be135-P695447_1-184.jpg","overallrank":"31787","overallscore":"143473","affiliate":"","division":1,"scores":[{"workoutrank":"30162","workoutresult":"--","scoreidentifier":"da2e15733f19a39d80e9","scoredisplay":"115 reps","scoredetails":{"time":1145,"breakdown":"10 DB Snatches\n15 Burpees\n20 DB Snatches\n15 Burpees\n30 DB Snatches\n15 Burpees\n10 DB Snatches\n\nJudged by Markku Sorosuo\nat CrossFit Naantali"},"video":"0"},{"workoutrank":"34527","workoutresult":"--","scoreidentifier":"1ba5c52d53f7937aaca2","scoredisplay":"78 reps - s","scoredetails":{"time":452,"breakdown":"2 Rounds\n50-ft lunges\n","judge":"Markku Sorosuo","affiliate":"CrossFit Naantali"},"video":0},{"workoutrank":"32414","workoutresult":"--","scoreidentifier":"8d0dfa601c8f37984d43","scoredisplay":"1 reps - s","scoredetails":{"time":1440,"breakdown":"0 Rounds\n1 Pull-ups","judge":"Markku Sorosuo","affiliate":"CrossFit Naantali"},"video":0},{"workoutrank":"24439","workoutresult":"--","scoreidentifier":"17993a457f4963808e1e","scoredisplay":"100 reps","scoredetails":{"time":332,"breakdown":"55 Deadlifts\n45 Wall-balls","judge":"Eliisa Lintunen","affiliate":"CrossFit Naantali"},"video":0},{"workoutrank":"21931","workoutresult":"--","scoreidentifier":"7d98a17ec2498b613854","scoredisplay":"159 reps","scoredetails":{"time":2400,"breakdown":"3 Rounds\n9 Thrusters\n18 Double-unders","judge":"Markku Sorosuo","affiliate":"CrossFit Naantali"},"video":0}]},{"userid":"896246","name":"Luca Apolloni","regionid":"7","affiliateid":"0","divisionid":"1","highlight":0,"age":29,"region":"Europe","height":"","weight":"","profilepic":"https:\/\/profilepicsbucket.crossfit.com\/a891d-P896246_1-184.jpg","overallrank":"31788","overallscore":"143474","affiliate":"","division":1,"scores":[{"workoutrank":"31336","workoutresult":"--","scoreidentifier":"45cc26188a00fc7362c3","scoredisplay":"15:16 - s","scoredetails":{"time":916,"breakdown":"225 reps"},"video":"1"},{"workoutrank":"29987","workoutresult":"--","scoreidentifier":"cc3885e2ea65fcebaa36","scoredisplay":"151 reps - s","scoredetails":{"time":611,"breakdown":"4 Rounds\n50-ft lunges\n5 Knee-raises\n"},"video":"1"},{"workoutrank":"25735","workoutresult":"--","scoreidentifier":"8f8765dfa89f7bd57cdf","scoredisplay":"142 reps - s","scoredetails":{"time":580,"breakdown":"11 Rounds\n9 Pull-ups\n1 Snatches"},"video":"1"},{"workoutrank":"31768","workoutresult":"--","scoreidentifier":"--","scoredisplay":"0","scoredetails":null,"video":"--"},{"workoutrank":"24648","workoutresult":"--","scoreidentifier":"60f1022fd59c41f0883c","scoredisplay":"10:39 - s","scoredetails":{"time":639,"breakdown":"440 reps"},"video":"1"}]},{"userid":"1092174","name":"Albert Rios","regionid":"7","affiliateid":"16916","divisionid":"1","highlight":0,"age":23,"region":"Europe","height":"167 cm","weight":"70 kg","profilepic":"https:\/\/profilepicsbucket.crossfit.com\/ff21f-P1092174_1-184.jpg","overallrank":"31788","overallscore":"143474","affiliate":"","division":1,"scores":[{"workoutrank":"32407","workoutresult":"--","scoreidentifier":"131f25a2065993465b62","scoredisplay":"16:48 - s","scoredetails":{"time":1008,"breakdown":"225 reps\nJudged by Jesus Ruiz\nat CrossFit L'H"},"video":"0"},{"workoutrank":"29031","workoutresult":"--","scoreidentifier":"a302d038bf229e17d563","scoredisplay":"174 reps - s","scoredetails":{"time":720,"breakdown":"5 Rounds\n20-ft lunges\n","judge":"Jesus Ruiz","affiliate":"CrossFit L'H"},"video":0},{"workoutrank":"27463","workoutresult":"--","scoreidentifier":"88eef44af8f748f1f9e1","scoredisplay":"105 reps - s","scoredetails":{"time":713,"breakdown":"8 Rounds\n8 Pull-ups\n1 Snatches","judge":"Jesus Ruiz","affiliate":"CrossFit L'H"},"video":0},{"workoutrank":"29669","workoutresult":"--","scoreidentifier":"5feda747fbf61d4a31c9","scoredisplay":"190 reps - s","scoredetails":{"time":679,"breakdown":"55 Deadlifts\n55 Wall-balls\n55 Calories\n25 Push-ups","judge":"Jesus Ruiz","affiliate":"CrossFit L'H"},"video":0},{"workoutrank":"24904","workoutresult":"--","scoreidentifier":"408f9bcde332d6c41229","scoredisplay":"10:55 - s","scoredetails":{"time":655,"breakdown":"440 reps","judge":"Jesus Ruiz","affiliate":"CrossFit L'H"},"video":0}]},{"userid":"455519","name":"Magnus Dirnberger","regionid":"7","affiliateid":"11576","divisionid":"18","highlight":0,"age":37,"region":"Europe","height":"180 cm","weight":"77 kg","profilepic":"https:\/\/profilepicsbucket.crossfit.com\/86f0e-P455519_1-184.jpg","overallrank":"31790","overallscore":"143477","affiliate":"","division":1,"scores":[{"workoutrank":"30379","workoutresult":"--","scoreidentifier":"5513c54f21fcf2e222bd","scoredisplay":"1 reps","scoredetails":{"time":1200,"breakdown":"1 DB Snatches\n\nJudged by Lisa Wieslander\nat CrossFit Naset"},"video":"0"},{"workoutrank":"27647","workoutresult":"--","scoreidentifier":"545ed4ae25773a0ffdba","scoredisplay":"1 reps","scoredetails":{"time":720,"breakdown":"0 Rounds\n5-ft lunges\n","judge":"Lisa Wieslander","affiliate":"CrossFit Naset"},"video":0},{"workoutrank":"24560","workoutresult":"--","scoreidentifier":"30e2ccb41fbe229c6a21","scoredisplay":"1 reps","scoredetails":{"time":1440,"breakdown":"0 Rounds\n1 Pull-ups","judge":"Lisa Wieslander","affiliate":"CrossFit Naset"},"video":0},{"workoutrank":"31768","workoutresult":"--","scoreidentifier":"--","scoredisplay":"0","scoredetails":null,"video":"--"},{"workoutrank":"29123","workoutresult":"--","scoreidentifier":"--","scoredisplay":"0","scoredetails":null,"video":"--"}]},{"userid":"1015121","name":"Maxoo Leconte","regionid":"7","affiliateid":"3993","divisionid":"1","highlight":0,"age":31,"region":"Europe","height":"188 cm","weight":"87 kg","profilepic":"https:\/\/profilepicsbucket.crossfit.com\/76b6e-P1015121_1-184.jpg","overallrank":"31790","overallscore":"143477","affiliate":"","division":1,"scores":[{"workoutrank":"30379","workoutresult":"--","scoreidentifier":"22662ada215d003dab9b","scoredisplay":"1 reps","scoredetails":{"time":1200,"breakdown":"1 DB Snatches\n\nJudged by David Lenouvel\nat Reebok CrossFit Louvre"},"video":"0"},{"workoutrank":"27647","workoutresult":"--","scoreidentifier":"bcdc56f0449f4e9ceef3","scoredisplay":"1 reps","scoredetails":{"time":720,"breakdown":"0 Rounds\n5-ft lunges\n","judge":"Julian Festor","affiliate":"Reebok CrossFit Louvre"},"video":0},{"workoutrank":"24560","workoutresult":"--","scoreidentifier":"1b8de6e117a455a73c5b","scoredisplay":"1 reps","scoredetails":{"time":1440,"breakdown":"0 Rounds\n1 Pull-ups","judge":"Julian Festor","affiliate":"Reebok CrossFit Louvre"},"video":0},{"workoutrank":"31768","workoutresult":"--","scoreidentifier":"--","scoredisplay":"0","scoredetails":null,"video":"--"},{"workoutrank":"29123","workoutresult":"--","scoreidentifier":"--","scoredisplay":"0","scoredetails":null,"video":"--"}]},{"userid":"1025434","name":"Alan Sherlock","regionid":"7","affiliateid":"6951","divisionid":"18","highlight":0,"age":35,"region":"Europe","height":"","weight":"","profilepic":"https:\/\/profilepicsbucket.crossfit.com\/pukie.png","overallrank":"31792","overallscore":"143479","affiliate":"","division":1,"scores":[{"workoutrank":"32390","workoutresult":"--","scoreidentifier":"cee6563cfcc10839dc25","scoredisplay":"16:47 - s","scoredetails":{"time":1007,"breakdown":"225 reps\nJudged by Maciej Grzechowiak\nat CrossFit Navitas"},"video":"0"},{"workoutrank":"29803","workoutresult":"--","scoreidentifier":"758645d939fc32e62053","scoredisplay":"158 reps - s","scoredetails":{"time":680,"breakdown":"4 Rounds\n50-ft lunges\n12 Knee-raises\n","judge":"Nikolett Barta","affiliate":"CrossFit Navitas"},"video":0},{"workoutrank":"23243","workoutresult":"--","scoreidentifier":"a18cc72b8d435d8d0d73","scoredisplay":"21 reps","scoredetails":{"time":480,"breakdown":"1 Rounds\n6 Pull-ups\n3 Snatches","judge":"Nikolett Barta","affiliate":"CrossFit Navitas"},"video":0},{"workoutrank":"28920","workoutresult":"--","scoreidentifier":"acac64161cf89f4cacff","scoredisplay":"199 reps - s","scoredetails":{"time":663,"breakdown":"55 Deadlifts\n55 Wall-balls\n55 Calories\n34 Push-ups","judge":"Maciej Grzechowiak","affiliate":"CrossFit Navitas"},"video":0},{"workoutrank":"29123","workoutresult":"--","scoreidentifier":"--","scoredisplay":"0","scoredetails":null,"video":"--"}]},{"userid":"923836","name":"Ivan Furlan Cano","regionid":"7","affiliateid":"14537","divisionid":"16","highlight":0,"age":16,"region":"Europe","height":"","weight":"","profilepic":"https:\/\/profilepicsbucket.crossfit.com\/5d3c7-P923836_2-184.jpg","overallrank":"31793","overallscore":"143489","affiliate":"","division":1,"scores":[{"workoutrank":"33563","workoutresult":"--","scoreidentifier":"02763c81e78b181de04c","scoredisplay":"18:09 - s","scoredetails":{"time":1089,"breakdown":"225 reps\nJudged by Felix Breitinger\nat CrossFit 2 Burgen"},"video":"0"},{"workoutrank":"29283","workoutresult":"--","scoreidentifier":"73d20150c54893e8de33","scoredisplay":"170 reps - s","scoredetails":{"time":717,"breakdown":"5 Rounds\n0-ft lunges\n","judge":"Fabian Weissenberger","affiliate":"CrossFit 2 Burgen"},"video":0},{"workoutrank":"26685","workoutresult":"--","scoreidentifier":"97bb7dd348a5b6102220","scoredisplay":"118 reps - s","scoredetails":{"time":687,"breakdown":"9 Rounds\n9 Pull-ups\n1 Snatches","judge":"Jacob Wallin","affiliate":"CrossFit 2 Burgen"},"video":0},{"workoutrank":"27920","workoutresult":"--","scoreidentifier":"4a5ca884e4e854eef406","scoredisplay":"211 reps - s","scoredetails":{"time":626,"breakdown":"55 Deadlifts\n55 Wall-balls\n55 Calories\n46 Push-ups","judge":"Benjamin Engerisser","affiliate":"CrossFit 2 Burgen"},"video":0},{"workoutrank":"26038","workoutresult":"--","scoreidentifier":"5bc99482793850346fd3","scoredisplay":"12:19 - s","scoredetails":{"time":739,"breakdown":"440 reps","judge":"Marcel Koob","affiliate":"CrossFit 2 Burgen"},"video":0}]},{"userid":"958172","name":"Cibr\u00e1n Santos","regionid":"7","affiliateid":"14317","divisionid":"1","highlight":0,"age":31,"region":"Europe","height":"182 cm","weight":"100 kg","profilepic":"https:\/\/profilepicsbucket.crossfit.com\/55284-P958172_1-184.jpg","overallrank":"31794","overallscore":"143492","affiliate":"","division":1,"scores":[{"workoutrank":"33395","workoutresult":"--","scoreidentifier":"f86e38041366d4c73dee","scoredisplay":"17:57 - s","scoredetails":{"time":1077,"breakdown":"225 reps\nJudged by Paulo Murua\nat CrossFit Runa"},"video":"0"},{"workoutrank":"32795","workoutresult":"--","scoreidentifier":"27d90b5a81ae17db2fa6","scoredisplay":"112 reps - s","scoredetails":{"time":618,"breakdown":"3 Rounds\n50-ft lunges\n","judge":"I\u00f1igo Razquin","affiliate":"CrossFit Runa"},"video":0},{"workoutrank":"24961","workoutresult":"--","scoreidentifier":"6e8e5cff992e817e3ff5","scoredisplay":"191 reps - s","scoredetails":{"time":1112,"breakdown":"15 Rounds\n11 Pull-ups","judge":"David Ust\u00e1rroz","affiliate":"CrossFit Runa"},"video":0},{"workoutrank":"28632","workoutresult":"--","scoreidentifier":"7709620e723ec4e79707","scoredisplay":"202 reps - s","scoredetails":{"time":556,"breakdown":"55 Deadlifts\n55 Wall-balls\n55 Calories\n37 Push-ups","judge":"Eugenijus Gendvilas","affiliate":"CrossFit Runa"},"video":0},{"workoutrank":"23709","workoutresult":"--","scoreidentifier":"cd51b1a7149d9a4e16e5","scoredisplay":"9:39 - s","scoredetails":{"time":579,"breakdown":"440 reps","judge":"I\u00f1igo Razquin","affiliate":"CrossFit Runa"},"video":0}]},{"userid":"1006916","name":"Barry O'Carroll","regionid":"7","affiliateid":"1132","divisionid":"1","highlight":0,"age":31,"region":"Europe","height":"","weight":"","profilepic":"https:\/\/profilepicsbucket.crossfit.com\/pukie.png","overallrank":"31795","overallscore":"143518","affiliate":"","division":1,"scores":[{"workoutrank":"31489","workoutresult":"--","scoreidentifier":"b20c165477d11bd5d1da","scoredisplay":"15:32 - s","scoredetails":{"time":932,"breakdown":"225 reps\nJudged by Barry Tonner\nat CrossFit Glasgow"},"video":"0"},{"workoutrank":"31604","workoutresult":"--","scoreidentifier":"c85878f351bb17a6f7af","scoredisplay":"125 reps - s","scoredetails":{"time":439,"breakdown":"3 Rounds\n50-ft lunges\n13 Pull-ups\n","judge":"Gavin Heselton","affiliate":"CrossFit Glasgow"},"video":0},{"workoutrank":"30796","workoutresult":"--","scoreidentifier":"fe934705899246c37e84","scoredisplay":"58 reps - s","scoredetails":{"time":240,"breakdown":"4 Rounds\n7 Pull-ups\n3 Snatches","judge":"Neil Mcmurchy","affiliate":"CrossFit Glasgow"},"video":0},{"workoutrank":"22030","workoutresult":"--","scoreidentifier":"6bb8f14d6cdc221810ed","scoredisplay":"138 reps","scoredetails":{"time":665,"breakdown":"55 Deadlifts\n55 Wall-balls\n28 Calories","judge":"Neil Mcmurchy","affiliate":"CrossFit Glasgow"},"video":0},{"workoutrank":"27599","workoutresult":"--","scoreidentifier":"1a434320479b91e20558","scoredisplay":"14:57 - s","scoredetails":{"time":897,"breakdown":"440 reps","judge":"Luke Wishart","affiliate":"CrossFit Glasgow"},"video":0}]},{"userid":"1016242","name":"Mike Kranenburg","regionid":"7","affiliateid":"4162","divisionid":"18","highlight":0,"age":38,"region":"Europe","height":"185 cm","weight":"73 kg","profilepic":"https:\/\/profilepicsbucket.crossfit.com\/adfe2-P1016242_1-184.jpg","overallrank":"31796","overallscore":"143519","affiliate":"","division":1,"scores":[{"workoutrank":"30927","workoutresult":"--","scoreidentifier":"d94fdd9bbd2e42fba9b9","scoredisplay":"14:25 - s","scoredetails":{"time":865,"breakdown":"225 reps\nJudged by Manuel Van Aacken\nat CrossFit Den Haag"},"video":"0"},{"workoutrank":"29334","workoutresult":"--","scoreidentifier":"b3d83f8c7cab24e91789","scoredisplay":"170 reps - s","scoredetails":{"time":720,"breakdown":"5 Rounds\n0-ft lunges\n","judge":"Manuel Van Aacken","affiliate":"CrossFit Den Haag"},"video":0},{"workoutrank":"32418","workoutresult":"--","scoreidentifier":"--","scoredisplay":"0","scoredetails":null,"video":"--"},{"workoutrank":"26960","workoutresult":"--","scoreidentifier":"4ef3882c0d2d27e9597f","scoredisplay":"232 reps - s","scoredetails":{"time":756,"breakdown":"1 Round\n12 Deadlifts","judge":"Manuel Van Aacken","affiliate":"CrossFit Den Haag"},"video":0},{"workoutrank":"23880","workoutresult":"--","scoreidentifier":"2c9fc5d7bdfb5bb21ca5","scoredisplay":"9:48 - s","scoredetails":{"time":588,"breakdown":"440 reps","judge":"Manuel Van Aacken","affiliate":"CrossFit Den Haag"},"video":0}]},{"userid":"756611","name":"Marc Padberg","regionid":"7","affiliateid":"2352","divisionid":"5","highlight":0,"age":52,"region":"Europe","height":"183 cm","weight":"82 kg","profilepic":"https:\/\/profilepicsbucket.crossfit.com\/7ab91-P756611_2-184.jpg","overallrank":"31797","overallscore":"143529","affiliate":"","division":1,"scores":[{"workoutrank":"28869","workoutresult":"--","scoreidentifier":"b28cef8ec440c175d8b7","scoredisplay":"154 reps","scoredetails":{"time":805,"breakdown":"10 DB Snatches\n15 Burpees\n20 DB Snatches\n15 Burpees\n30 DB Snatches\n15 Burpees\n40 DB Snatches\n9 Burpees\n\nJudged by Vincent Bruning\nat CrossFit Twente"},"video":"0"},{"workoutrank":"26577","workoutresult":"--","scoreidentifier":"f9fcef58577035f42f4a","scoredisplay":"69 reps","scoredetails":{"time":703,"breakdown":"2 Rounds\n5-ft lunges\n","judge":"Dylan Ye","affiliate":"CrossFit Twente"},"video":0},{"workoutrank":"27192","workoutresult":"--","scoreidentifier":"6d8aa622b42d9ef85e6c","scoredisplay":"106 reps - s","scoredetails":{"time":440,"breakdown":"8 Rounds\n8 Pull-ups\n2 Snatches","judge":"Ruud Boom","affiliate":"CrossFit Twente"},"video":0},{"workoutrank":"31768","workoutresult":"--","scoreidentifier":"--","scoredisplay":"0","scoredetails":null,"video":"--"},{"workoutrank":"29123","workoutresult":"--","scoreidentifier":"--","scoredisplay":"0","scoredetails":null,"video":"--"}]},{"userid":"942706","name":"Steffen Burbank","regionid":"7","affiliateid":"5657","divisionid":"1","highlight":0,"age":34,"region":"Europe","height":"191 cm","weight":"95 kg","profilepic":"https:\/\/profilepicsbucket.crossfit.com\/pukie.png","overallrank":"31798","overallscore":"143532","affiliate":"","division":1,"scores":[{"workoutrank":"26743","workoutresult":"--","scoreidentifier":"b20b0641392bc06c6834","scoredisplay":"173 reps","scoredetails":{"time":1121,"breakdown":"10 DB Snatches\n15 Burpees\n20 DB Snatches\n15 Burpees\n30 DB Snatches\n15 Burpees\n40 DB Snatches\n15 Burpees\n13 DB Snatches\n\nJudged by Florian Wagner\nat CrossFit 108"},"video":"0"},{"workoutrank":"23480","workoutresult":"--","scoreidentifier":"358a629e39113b29aa95","scoredisplay":"78 reps","scoredetails":{"time":440,"breakdown":"2 Rounds\n50-ft lunges\n","judge":"Frank Ladewig","affiliate":"CrossFit 108"},"video":0},{"workoutrank":"32418","workoutresult":"--","scoreidentifier":"--","scoredisplay":"0","scoredetails":null,"video":"--"},{"workoutrank":"31768","workoutresult":"--","scoreidentifier":"--","scoredisplay":"0","scoredetails":null,"video":"--"},{"workoutrank":"29123","workoutresult":"--","scoreidentifier":"--","scoredisplay":"0","scoredetails":null,"video":"--"}]},{"userid":"991735","name":"Wouter Oeyen","regionid":"7","affiliateid":"18589","divisionid":"1","highlight":0,"age":22,"region":"Europe","height":"178 cm","weight":"91 kg","profilepic":"https:\/\/profilepicsbucket.crossfit.com\/75ef3-P991735_1-184.jpg","overallrank":"31799","overallscore":"143534","affiliate":"","division":1,"scores":[{"workoutrank":"23548","workoutresult":"--","scoreidentifier":"24fb9c7896ba4453d61e","scoredisplay":"192 reps","scoredetails":{"time":1119,"breakdown":"10 DB Snatches\n15 Burpees\n20 DB Snatches\n15 Burpees\n30 DB Snatches\n15 Burpees\n40 DB Snatches\n15 Burpees\n32 DB Snatches\n\nJudged by Jef Knaeps\nat CrossFit Blue Fenix"},"video":"0"},{"workoutrank":"26913","workoutresult":"--","scoreidentifier":"a14bdcc66e1031fff568","scoredisplay":"59 reps","scoredetails":{"time":720,"breakdown":"1 Rounds\n50-ft lunges\n15 T2B\n","judge":"Joel Leysen","affiliate":"CrossFit Blue Fenix"},"video":0},{"workoutrank":"32418","workoutresult":"--","scoreidentifier":"--","scoredisplay":"0","scoredetails":null,"video":"--"},{"workoutrank":"31532","workoutresult":"--","scoreidentifier":"f360b09a346a8119e39d","scoredisplay":"131 reps - s","scoredetails":{"time":780,"breakdown":"55 Deadlifts\n55 Wall-balls\n21 Calories","judge":"Joel Leysen","affiliate":"CrossFit Blue Fenix"},"video":0},{"workoutrank":"29123","workoutresult":"--","scoreidentifier":"--","scoredisplay":"0","scoredetails":null,"video":"--"}]},{"userid":"717685","name":"Knut Eskeland","regionid":"7","affiliateid":"9082","divisionid":"18","highlight":0,"age":35,"region":"Europe","height":"","weight":"","profilepic":"https:\/\/profilepicsbucket.crossfit.com\/pukie.png","overallrank":"31800","overallscore":"143540","affiliate":"","division":1,"scores":[{"workoutrank":"26713","workoutresult":"--","scoreidentifier":"8970bc5b195dc57043f2","scoredisplay":"173 reps","scoredetails":{"time":1092,"breakdown":"10 DB Snatches\n15 Burpees\n20 DB Snatches\n15 Burpees\n30 DB Snatches\n15 Burpees\n40 DB Snatches\n15 Burpees\n13 DB Snatches\n\nJudged by Nora Svenningsen\nat Grenland CrossFit"},"video":"0"},{"workoutrank":"34748","workoutresult":"--","scoreidentifier":"--","scoredisplay":"0","scoredetails":null,"video":"--"},{"workoutrank":"21188","workoutresult":"--","scoreidentifier":"746e5398e905e8e2a2d6","scoredisplay":"39 reps","scoredetails":{"time":464,"breakdown":"3 Rounds\n3 Pull-ups","judge":"Jonas Fiskum Pedersen","affiliate":"Grenland CrossFit"},"video":0},{"workoutrank":"31768","workoutresult":"--","scoreidentifier":"--","scoredisplay":"0","scoredetails":null,"video":"--"},{"workoutrank":"29123","workoutresult":"--","scoreidentifier":"--","scoredisplay":"0","scoredetails":null,"video":"--"}]}],"query":{"division":1,"region":7,"occupation":"0","scaled":0,"sort":0,"page":636},"cacheKey":"v2.leaderboard.OPN-2017-DIV01-FIT01007-PRF00-RXD.0.636"}